MANIFEST.in
README.md
setup.py
launch_pad.egg-info/PKG-INFO
launch_pad.egg-info/SOURCES.txt
launch_pad.egg-info/dependency_links.txt
launch_pad.egg-info/entry_points.txt
launch_pad.egg-info/not-zip-safe
launch_pad.egg-info/requires.txt
launch_pad.egg-info/top_level.txt
launchpad/__init__.py
launchpad/launchpad.py
launchpad/job/__init__.py
launchpad/job/base.py
launchpad/job/color.py
launchpad/job/master_job.py
launchpad/job/nni_job.py
launchpad/job/shell_job.py
launchpad/job/slurm_job.py
launchpad/job/util.py
launchpad/job/scripts/sbatch_template.sh
launchpad/util/__init__.py
launchpad/util/config.py