Metadata-Version: 1.1
Name: launch-pad
Version: 1.2.2
Summary: A tool that automatically compile and launch slurm jobs                  based on a YAML configuration file.
Home-page: https://github.com/stanfordmlgroup/LaunchPad
Author: Hao Sheng
Author-email: haosheng@stanford.edu
License: Expat License
Keywords: automation,sbatch
Platform: UNKNOWN
Classifier: Development Status :: 5 - Production/Stable
Classifier: Environment :: Console
Classifier: Intended Audience :: Developers
Classifier: License :: OSI Approved :: MIT License
Classifier: Operating System :: OS Independent
Classifier: Programming Language :: Python
Classifier: Programming Language :: Python :: 3.6
Classifier: Programming Language :: Python :: 3.7
Classifier: Programming Language :: Python :: 3.8
